{
  "timestamp": "2025-08-11T21:32:15Z",
  "route_status": {"health": "MISSING","topic": "EXISTS","predict": "EXISTS","agent_chat": "EXISTS","predictions": "EXISTS"},
  "issues_found": [
    "Health route was missing - now created",
    "Need to verify other route implementations",
    "Check if routes require authentication"
  ],
  "actions_taken": [
    "Created /api/health route",
    "Tested build after changes",
    "Committed changes to git"
  ],
  "build_result": "success",
  "next_steps": [
    "Redeploy to Vercel",
    "Test health endpoint",
    "Check authentication on other routes"
  ]
}
